razor/__init__.py
razor/config.py
razor/driver.py
razor/echo.py
razor/interface.py
razor/passes.py
razor/pool.py
razor/provenance.py
razor/rop_guided_dce.py
razor/slash.py
razor/stringbuffer.py
razor/utils.py
razor/version.py
razor/proto/Previrt_pb2.py
razor/proto/__init__.py
razor-1.1.2.dist-info/LICENSE
razor-1.1.2.dist-info/METADATA
razor-1.1.2.dist-info/WHEEL
razor-1.1.2.dist-info/entry_points.txt
razor-1.1.2.dist-info/top_level.txt
razor-1.1.2.dist-info/RECORD
