Metadata-Version: 2.1
Name: razor
Version: 1.1.2
Summary: The OCCAM saga
Home-page: https://github.com/SRI-CSL/OCCAM
Author: Ian A. Mason
Author-email: iam@csl.sri.com
License: MIT
Platform: UNKNOWN
Classifier: Development Status :: 3 - Alpha
Classifier: Natural Language :: English
Classifier: Intended Audience :: Developers
Classifier: Topic :: System :: Distributed Computing
Classifier: License :: OSI Approved :: MIT License
Classifier: Programming Language :: Python
Classifier: Programming Language :: Python :: 3
Requires-Python: >=3.6
